sorotraj/__init__.py
sorotraj/build_traj.py
sorotraj/interpolator.py
sorotraj/utils.py
sorotraj-1.3.2.dist-info/METADATA
sorotraj-1.3.2.dist-info/WHEEL
sorotraj-1.3.2.dist-info/top_level.txt
sorotraj-1.3.2.dist-info/RECORD
