Metadata-Version: 2.1
Name: sorotraj
Version: 1.3.2
Summary: Generate trajectories for soft robots from a file
Home-page: https://github.com/harvard-microrobotics/sorotraj
Author: Clark Teeple
Author-email: cbteeple@gmail.com
License: MIT
Platform: UNKNOWN
Requires-Dist: numpy
Requires-Dist: scipy
Requires-Dist: matplotlib
Requires-Dist: pyyaml
